{
  "TranslationProperties": {
    "Name": "server.items.Ingredient_Dust_Essence.name",
    "Description": "server.items.Ingredient_Dust_Essence.description"
  },
  "Quality": "Uncommon",
  "Categories": [
    "Items.Ingredients"
  ],
  "Model": "Resources/Ingredients/Essence.blockymodel",
  "Texture": "Resources/Ingredients/Essence_Textures/Dust_Essence_Texture.png",
  "PlayerAnimationsId": "Item",
  "IconProperties": {
    "Scale": 0.6,
    "Rotation": [
      0,
      0,
      0
    ],
    "Translation": [
      0,
      -13
    ]
  },
  "Tags": {
    "Type": [
      "Ingredient"
    ]
  },
  "ItemEntity": {
    "ParticleSystemId": null
  },
  "Scale": 0.8,
  "Light": {
    "Color": "#310",
    "Radius": 1
  },
  "ItemSoundSetId": "ISS_Items_Gems",
  "DropOnDeath": true,
  "Icon": "Icons/ItemsGenerated/Ingredient_Dust_Essence.png"
}
